schema_markdown/__init__.py
schema_markdown/encode.py
schema_markdown/parser.py
schema_markdown/schema.py
schema_markdown/schema_util.py
schema_markdown/type_model.py
schema_markdown-1.2.11.dist-info/licenses/LICENSE
schema_markdown-1.2.11.dist-info/METADATA
schema_markdown-1.2.11.dist-info/WHEEL
schema_markdown-1.2.11.dist-info/top_level.txt
schema_markdown-1.2.11.dist-info/RECORD
