Metadata-Version: 2.4
Name: schema-markdown
Version: 1.2.11
Summary: A schema definition and validation library
Home-page: https://github.com/craigahobbs/schema-markdown
Author: Craig A. Hobbs
Author-email: craigahobbs@gmail.com
License: MIT
Keywords: schema,validate,json
Classifier: Development Status :: 5 - Production/Stable
Classifier: Intended Audience :: Developers
Classifier: Operating System :: OS Independent
Classifier: Programming Language :: Python :: 3.9
Classifier: Programming Language :: Python :: 3.10
Classifier: Programming Language :: Python :: 3.11
Classifier: Programming Language :: Python :: 3.12
Classifier: Programming Language :: Python :: 3.13
Classifier: Programming Language :: Python :: 3.14
Classifier: Topic :: Utilities
License-File: LICENSE
Dynamic: license-file
